{
  "version" : "2",
  "id" : "7d570373-f9f2-467a-bd74-530949b54778",
  "experiment" : {
    "base" : {
      "analysis" : {
        "variableFilters" : [ ],
        "selectedType" : "dynamic",
        "choices" : [ {
          "type" : "dynamic",
          "parameters" : {
            "final_time" : 6900,
            "interval" : 13.8,
            "start_time" : 0
          },
          "simulationOptions" : {
            "dynamic_diagnostics" : false,
            "ncp" : 500
          },
          "solverOptions" : { },
          "compilerOptions" : {
            "c_compiler" : "gcc",
            "generate_html_diagnostics" : false,
            "include_protected_variables" : false
          },
          "runtimeOptions" : { }
        } ]
      },
      "modifiers" : {
        "initializeFrom" : "",
        "variables" : [ ]
      }
    }
  },
  "metadata" : {
    "created" : "2023-10-23 10:50:55.557334263",
    "lastModified" : "2023-10-25T14:11:54.248574923Z",
    "name" : "NoFiltering"
  }
}